{
    "properties": {
        "admittance_matrix": {
            "items": {
                "items": {
                    "maxItems": 2,
                    "minItems": 2,
                    "prefixItems": [
                        {
                            "type": "number"
                        },
                        {
                            "type": "number"
                        }
                    ],
                    "type": "array"
                },
                "type": "array"
            },
            "title": "Admittance Matrix",
            "type": "array"
        },
        "ids": {
            "items": {
                "type": "string"
            },
            "title": "Ids",
            "type": "array"
        },
        "units": {
            "default": "S",
            "title": "Units",
            "type": "string"
        }
    },
    "required": [
        "admittance_matrix",
        "ids"
    ],
    "title": "AdmittanceMatrix",
    "type": "object"
}